PyPDump/LICENSE
PyPDump/README.MD
PyPDump/__init__.py
PyPDump/requirements.txt
PyPDump/thirdparty.json
PyPDump-0.31.dist-info/LICENSE.rst
PyPDump-0.31.dist-info/METADATA
PyPDump-0.31.dist-info/WHEEL
PyPDump-0.31.dist-info/top_level.txt
PyPDump-0.31.dist-info/RECORD
